Workbook

Sheet Metrics
A1: E-Commerce Website - Manual Testing and Test Metrics Analysis
A2: All results are formulas driven by the Test Cases, Requirements, Defects and Response Times sheets. Blue = editable input.
A4: Input
A5: Software size (LOC) | B5: 20000 | C5: Assumption from the problem statement: 20,000 lines of code.
A6: KLOC | B6: =B5/1000 -> 20
A8: Metrics and evaluations
A9: Metric | B9: Formula | C9: Value 1 | D9: Value 2 | E9: Result | F9: Evaluation
A10: 1. Test Coverage | B10: (Requirements tested / Total requirements) x 100 | C10: =COUNTIF(Requirements!$G$2:$G$15,"Yes") -> 14 | D10: =COUNTA(Requirements!$A$2:$A$15) -> 14 | E10: =IF(D10=0,0,C10/D10) -> 1 | F10: All requirements have been covered by at least one test case.
A11: 2. Test Execution % | B11: (Executed / Total test cases) x 100 | C11: =COUNTIF('Test Cases'!$G$2:$G$174,"Pass")+COUNTIF('Test Cases'!$G$2:$G$174,"Fail") -> 173 | D11: =COUNTA('Test Cases'!$A$2:$A$174) -> 173 | E11: =IF(D11=0,0,C11/D11) -> 1 | F11: All planned test cases were executed.
A12: 3. Pass Rate | B12: (Passed / Executed) x 100 | C12: =COUNTIF('Test Cases'!$G$2:$G$174,"Pass") -> 163 | D12: =C11 -> 173 | E12: =IF(D12=0,0,C12/D12) -> 0.94219653 | F12: Most test cases passed successfully.
A13: 4. Fail Rate | B13: (Failed / Executed) x 100 | C13: =COUNTIF('Test Cases'!$G$2:$G$174,"Fail") -> 10 | D13: =C11 -> 173 | E13: =IF(D13=0,0,C13/D13) -> 0.057803468 | F13: Failed test cases need defect analysis and retesting.
A14: 5. Defect Density | B14: Unique defects / KLOC | C14: =COUNTA(Defects!$A$2:$A$9) -> 8 | D14: =B6 -> 20 | E14: =IF(D14=0,0,C14/D14) -> 0.4 | F14: Failed test cases do not equal defects: several failures can share one defect (10 failed cases -> 8 unique defects).
A15: 6. Mean (page loading) | B15: Sum of values / Number of values | C15: =SUM('Response Times'!$B$2:$B$6) -> 20 | D15: =COUNT('Response Times'!$B$2:$B$6) -> 5 | E15: =IF(D15=0,0,C15/D15) -> 4 | F15: The average page-loading time.
A16: 7. Median (page loading) | B16: Middle value of sorted data | C16: Sorted: 2, 3, 3, 4, 8 | D16: =COUNT('Response Times'!$B$2:$B$6) -> 5 | E16: =MEDIAN('Response Times'!$B$2:$B$6) -> 3 | F16: The typical page-loading time.
A17: 8. Mean vs Median | B17: Mean - Median | C17: =E15 -> 4 | D17: =E16 -> 3 | E17: =C17-D17 -> 1 | F17: Mean is higher because the 8-second value increases the average; investigate it as a possible performance issue.
A18: 9. Critical Defect % | B18: (Critical defects / Total defects) x 100 | C18: =COUNTIF(Defects!$E$2:$E$9,"Critical") -> 2 | D18: =C14 -> 8 | E18: =IF(D18=0,0,C18/D18) -> 0.25 | F18: Critical defects must be addressed with high priority before release.
A20: 10. Defect Distribution
A21: Severity | B21: Calculation | C21: Defects | D21: Total defects | E21: Distribution | F21: Evaluation
A22: Critical | B22: =C22&"/"&D22&" x 100" -> 2/8 x 100 | C22: =COUNTIF(Defects!$E$2:$E$9,A22) -> 2 | D22: =$C$14 -> 8 | E22: =IF(D22=0,0,C22/D22) -> 0.25 | F22: =IF(MAX(C22:C25)=C24,"Most defects are Medium severity ("&TEXT(E24,"0.0%")&"), followed by Critical and High defects. ","")&"Fix critical and high-severity defects before release, then retest the affected modules." -> Most defects are Medium severity (37.5%), followed by Critical and High defects. Fix critical and high-severity defects before release, then retest the affected modules.
A23: High | B23: =C23&"/"&D23&" x 100" -> 2/8 x 100 | C23: =COUNTIF(Defects!$E$2:$E$9,A23) -> 2 | D23: =$C$14 -> 8 | E23: =IF(D23=0,0,C23/D23) -> 0.25
A24: Medium | B24: =C24&"/"&D24&" x 100" -> 3/8 x 100 | C24: =COUNTIF(Defects!$E$2:$E$9,A24) -> 3 | D24: =$C$14 -> 8 | E24: =IF(D24=0,0,C24/D24) -> 0.375
A25: Low | B25: =C25&"/"&D25&" x 100" -> 1/8 x 100 | C25: =COUNTIF(Defects!$E$2:$E$9,A25) -> 1 | D25: =$C$14 -> 8 | E25: =IF(D25=0,0,C25/D25) -> 0.125
A26: Total | C26: =SUM(C22:C25) -> 8 | D26: =C14 -> 8 | E26: =SUM(E22:E25) -> 1
A28: 11. Final Metrics Summary
A29: Metric | B29: Result
A30: Test Coverage | B30: =E10 -> 1
A31: Test Execution % | B31: =E11 -> 1
A32: Pass Rate | B32: =E12 -> 0.94219653
A33: Fail Rate | B33: =E13 -> 0.057803468
A34: Unique Defects | B34: =C14 -> 8
A35: Defect Density | B35: =E14 -> 0.4
A36: Mean Page Loading Time | B36: =E15 -> 4
A37: Median Page Loading Time | B37: =E16 -> 3
A38: Critical Defect % | B38: =E18 -> 0.25
A39: Critical Defects | B39: =C22 -> 2
A40: High Defects | B40: =C23 -> 2
A41: Medium Defects | B41: =C24 -> 3
A42: Low Defects | B42: =C25 -> 1
A44: Final Evaluation
A45: ="The e-commerce website achieved "&TEXT(E10,"0%")&" requirement coverage and "&TEXT(E11,"0%")&" test execution. Out of "&D11&" test cases, "&C12&" passed and "&C13&" failed, giving a pass rate of "&TEXT(E12,"0.00%")&" and fail rate of "&TEXT(E13,"0.00%")&". "&C14&" unique defects were identified, with a defect density of "&TEXT(E14,"0.0")&" defects/KLOC. The mean and median page-loading times were "&TEXT(E15,"0")&" seconds and "&TEXT(E16,"0")&" seconds respectively. Critical defects accounted for "&TEXT(E18,"0%")&" of all defects. The failed test cases and critical/high-severity defects should be fixed and regression-tested before release." -> The e-commerce website achieved 100% requirement coverage and 100% test execution. Out of 173 test cases, 163 passed and 10 failed, giving a pass rate of 94.22% and fail rate of 5.78%. 8 unique defects were identified, with a defect density of 0.4 defects/KLOC. The mean and median page-loading times were 4 seconds and 3 seconds respectively. Critical defects accounted for 25% of all defects. The failed test cases and critical/high-severity defects should be fixed and regression-tested before release.

Sheet Module Summary
A1: Module | B1: Total TCs | C1: Passed | D1: Failed | E1: Not Run / Blocked | F1: Pass % (of executed)
A2: Registration | B2: =COUNTIF('Test Cases'!$B$2:$B$174,A2) -> 18 | C2: =COUNTIFS('Test Cases'!$B$2:$B$174,A2,'Test Cases'!$G$2:$G$174,"Pass") -> 18 | D2: =COUNTIFS('Test Cases'!$B$2:$B$174,A2,'Test Cases'!$G$2:$G$174,"Fail") -> 0 | E2: =B2-C2-D2 -> 0 | F2: =IF(C2+D2=0,0,C2/(C2+D2)) -> 1
A3: Login | B3: =COUNTIF('Test Cases'!$B$2:$B$174,A3) -> 15 | C3: =COUNTIFS('Test Cases'!$B$2:$B$174,A3,'Test Cases'!$G$2:$G$174,"Pass") -> 15 | D3: =COUNTIFS('Test Cases'!$B$2:$B$174,A3,'Test Cases'!$G$2:$G$174,"Fail") -> 0 | E3: =B3-C3-D3 -> 0 | F3: =IF(C3+D3=0,0,C3/(C3+D3)) -> 1
A4: Home Page | B4: =COUNTIF('Test Cases'!$B$2:$B$174,A4) -> 12 | C4: =COUNTIFS('Test Cases'!$B$2:$B$174,A4,'Test Cases'!$G$2:$G$174,"Pass") -> 11 | D4: =COUNTIFS('Test Cases'!$B$2:$B$174,A4,'Test Cases'!$G$2:$G$174,"Fail") -> 1 | E4: =B4-C4-D4 -> 0 | F4: =IF(C4+D4=0,0,C4/(C4+D4)) -> 0.91666667
A5: Product Search | B5: =COUNTIF('Test Cases'!$B$2:$B$174,A5) -> 15 | C5: =COUNTIFS('Test Cases'!$B$2:$B$174,A5,'Test Cases'!$G$2:$G$174,"Pass") -> 14 | D5: =COUNTIFS('Test Cases'!$B$2:$B$174,A5,'Test Cases'!$G$2:$G$174,"Fail") -> 1 | E5: =B5-C5-D5 -> 0 | F5: =IF(C5+D5=0,0,C5/(C5+D5)) -> 0.93333333
A6: Product Details | B6: =COUNTIF('Test Cases'!$B$2:$B$174,A6) -> 20 | C6: =COUNTIFS('Test Cases'!$B$2:$B$174,A6,'Test Cases'!$G$2:$G$174,"Pass") -> 19 | D6: =COUNTIFS('Test Cases'!$B$2:$B$174,A6,'Test Cases'!$G$2:$G$174,"Fail") -> 1 | E6: =B6-C6-D6 -> 0 | F6: =IF(C6+D6=0,0,C6/(C6+D6)) -> 0.95
A7: Filter & Sort | B7: =COUNTIF('Test Cases'!$B$2:$B$174,A7) -> 15 | C7: =COUNTIFS('Test Cases'!$B$2:$B$174,A7,'Test Cases'!$G$2:$G$174,"Pass") -> 14 | D7: =COUNTIFS('Test Cases'!$B$2:$B$174,A7,'Test Cases'!$G$2:$G$174,"Fail") -> 1 | E7: =B7-C7-D7 -> 0 | F7: =IF(C7+D7=0,0,C7/(C7+D7)) -> 0.93333333
A8: Cart | B8: =COUNTIF('Test Cases'!$B$2:$B$174,A8) -> 20 | C8: =COUNTIFS('Test Cases'!$B$2:$B$174,A8,'Test Cases'!$G$2:$G$174,"Pass") -> 18 | D8: =COUNTIFS('Test Cases'!$B$2:$B$174,A8,'Test Cases'!$G$2:$G$174,"Fail") -> 2 | E8: =B8-C8-D8 -> 0 | F8: =IF(C8+D8=0,0,C8/(C8+D8)) -> 0.9
A9: Wishlist | B9: =COUNTIF('Test Cases'!$B$2:$B$174,A9) -> 8 | C9: =COUNTIFS('Test Cases'!$B$2:$B$174,A9,'Test Cases'!$G$2:$G$174,"Pass") -> 8 | D9: =COUNTIFS('Test Cases'!$B$2:$B$174,A9,'Test Cases'!$G$2:$G$174,"Fail") -> 0 | E9: =B9-C9-D9 -> 0 | F9: =IF(C9+D9=0,0,C9/(C9+D9)) -> 1
A10: Checkout | B10: =COUNTIF('Test Cases'!$B$2:$B$174,A10) -> 15 | C10: =COUNTIFS('Test Cases'!$B$2:$B$174,A10,'Test Cases'!$G$2:$G$174,"Pass") -> 14 | D10: =COUNTIFS('Test Cases'!$B$2:$B$174,A10,'Test Cases'!$G$2:$G$174,"Fail") -> 1 | E10: =B10-C10-D10 -> 0 | F10: =IF(C10+D10=0,0,C10/(C10+D10)) -> 0.93333333
A11: Payment | B11: =COUNTIF('Test Cases'!$B$2:$B$174,A11) -> 15 | C11: =COUNTIFS('Test Cases'!$B$2:$B$174,A11,'Test Cases'!$G$2:$G$174,"Pass") -> 12 | D11: =COUNTIFS('Test Cases'!$B$2:$B$174,A11,'Test Cases'!$G$2:$G$174,"Fail") -> 3 | E11: =B11-C11-D11 -> 0 | F11: =IF(C11+D11=0,0,C11/(C11+D11)) -> 0.8
A12: Order | B12: =COUNTIF('Test Cases'!$B$2:$B$174,A12) -> 10 | C12: =COUNTIFS('Test Cases'!$B$2:$B$174,A12,'Test Cases'!$G$2:$G$174,"Pass") -> 10 | D12: =COUNTIFS('Test Cases'!$B$2:$B$174,A12,'Test Cases'!$G$2:$G$174,"Fail") -> 0 | E12: =B12-C12-D12 -> 0 | F12: =IF(C12+D12=0,0,C12/(C12+D12)) -> 1
A13: Profile | B13: =COUNTIF('Test Cases'!$B$2:$B$174,A13) -> 10 | C13: =COUNTIFS('Test Cases'!$B$2:$B$174,A13,'Test Cases'!$G$2:$G$174,"Pass") -> 10 | D13: =COUNTIFS('Test Cases'!$B$2:$B$174,A13,'Test Cases'!$G$2:$G$174,"Fail") -> 0 | E13: =B13-C13-D13 -> 0 | F13: =IF(C13+D13=0,0,C13/(C13+D13)) -> 1
A14: Total | B14: =SUM(B2:B13) -> 173 | C14: =SUM(C2:C13) -> 163 | D14: =SUM(D2:D13) -> 10 | E14: =SUM(E2:E13) -> 0 | F14: =IF(C14+D14=0,0,C14/(C14+D14)) -> 0.94219653
A16: Use the Failed column to see where failures concentrate and which modules need extra testing and regression.

Sheet Test Cases
A1: TC ID | B1: Module | C1: Req ID | D1: Test Case | E1: Expected Result | F1: Actual Result | G1: Status | H1: Defect ID
A2: REG-01 | B2: Registration | C2: R01 | D2: Register with valid details | E2: Account created | F2: As expected | G2: Pass
A3: REG-02 | B3: Registration | C3: R01 | D3: Leave name blank | E3: Validation displayed | F3: As expected | G3: Pass
A4: REG-03 | B4: Registration | C4: R01 | D4: Leave email blank | E4: Validation displayed | F4: As expected | G4: Pass
A5: REG-04 | B5: Registration | C5: R01 | D5: Leave password blank | E5: Validation displayed | F5: As expected | G5: Pass
A6: REG-05 | B6: Registration | C6: R01 | D6: Enter invalid email | E6: Email validation displayed | F6: As expected | G6: Pass
A7: REG-06 | B7: Registration | C7: R01 | D7: Enter existing email | E7: Account creation rejected | F7: As expected | G7: Pass
A8: REG-07 | B8: Registration | C8: R01 | D8: Enter password below minimum length | E8: Validation displayed | F8: As expected | G8: Pass
A9: REG-08 | B9: Registration | C9: R01 | D9: Enter valid strong password | E9: Password accepted | F9: As expected | G9: Pass
A10: REG-09 | B10: Registration | C10: R01 | D10: Enter mismatched confirm password | E10: Error displayed | F10: As expected | G10: Pass
A11: REG-10 | B11: Registration | C11: R01 | D11: Enter valid matching passwords | E11: Registration succeeds | F11: As expected | G11: Pass
A12: REG-11 | B12: Registration | C12: R01 | D12: Enter alphabets in phone field | E12: Invalid input rejected | F12: As expected | G12: Pass
A13: REG-12 | B13: Registration | C13: R01 | D13: Enter invalid phone number | E13: Validation displayed | F13: As expected | G13: Pass
... A45: HOME-11 | B45: Home Page | C45: R03 | D45: Open home page on mobile | E45: Layout works correctly | F45: As expected | G45: Pass
A46: HOME-12 | B46: Home Page | C46: R03 | D46: Check broken images | E46: No broken images | F46: Broken image on home page | G46: Fail | H46: D08
A47: SRCH-01 | B47: Product Search | C47: R04 | D47: Search valid product | E47: Product displayed | F47: As expected | G47: Pass
A48: SRCH-02 | B48: Product Search | C48: R04 | D48: Search invalid product | E48: No-results message | F48: As expected | G48: Pass
A49: SRCH-03 | B49: Product Search | C49: R04 | D49: Search partial product name | E49: Relevant products displayed | F49: As expected | G49: Pass
A50: SRCH-04 | B50: Product Search | C50: R04 | D50: Search using uppercase | E50: Search works | F50: As expected | G50: Pass
A51: SRCH-05 | B51: Product Search | C51: R04 | D51: Search using lowercase | E51: Search works | F51: As expected | G51: Pass
A52: SRCH-06 | B52: Product Search | C52: R04 | D52: Search with numbers | E52: Appropriate results displayed | F52: As expected | G52: Pass
A53: SRCH-07 | B53: Product Search | C53: R04 | D53: Search with special characters | E53: Input handled safely | F53: As expected | G53: Pass
A54: SRCH-08 | B54: Product Search | C54: R04 | D54: Search with spaces | E54: Input handled correctly | F54: As expected | G54: Pass
A55: SRCH-09 | B55: Product Search | C55: R04 | D55: Empty search | E55: Validation/appropriate result | F55: Empty search shows all products, no message | G55: Fail | H55: D07
A56: SRCH-10 | B56: Product Search | C56: R04 | D56: Very long search text | E56: Application handles input safely | F56: As expected | G56: Pass
A57: SRCH-11 | B57: Product Search | C57: R04 | D57: Search by product ID/SKU | E57: Correct product displayed | F57: As expected | G57: Pass
A58: SRCH-12 | B58: Product Search | C58: R04 | D58: Clear search | E58: Search field/results reset | F58: As expected | G58: Pass
A59: SRCH-13 | B59: Product Search | C59: R04 | D59: Search suggestions | E59: Relevant suggestions displayed | F59: As expected | G59: Pass
A60: SRCH-14 | B60: Product Search | C60: R04 | D60: Select search suggestion | E60: Correct results/product opens | F60: As expected | G60: Pass
A61: SRCH-15 | B61: Product Search | C61: R04 | D61: Search with spelling variation | E61: Appropriate results/suggestions | F61: As expected | G61: Pass
A62: PROD-01 | B62: Product Details | C62: R05 | D62: Open product | E62: Correct details page opens | F62: As expected | G62: Pass
A63: PROD-02 | B63: Product Details | C63: R05 | D63: Verify product name | E63: Correct name displayed | F63: As expected | G63: Pass
A64: PROD-03 | B64: Product Details | C64: R05 | D64: Verify product image | E64: Correct image displayed | F64: As expected | G64: Pass
A65: PROD-04 | B65: Product Details | C65: R05 | D65: Zoom product image | E65: Image enlarges | F65: As expected | G65: Pass
A66: PROD-05 | B66: Product Details | C66: R05 | D66: Verify product description | E66: Correct description displayed | F66: As expected | G66: Pass
A67: PROD-06 | B67: Product Details | C67: R05 | D67: Verify price | E67: Correct price displayed | F67: As expected | G67: Pass
... A75: PROD-14 | B75: Product Details | C75: R05 | D75: Add available product to cart | E75: Product added | F75: As expected | G75: Pass
A76: PROD-15 | B76: Product Details | C76: R05 | D76: Add out-of-stock product | E76: Product cannot be purchased | F76: Out-of-stock product can be purchased | G76: Fail | H76: D03
A77: PROD-16 | B77: Product Details | C77: R05 | D77: Increase quantity | E77: Quantity increases | F77: As expected | G77: Pass
A78: PROD-17 | B78: Product Details | C78: R05 | D78: Decrease quantity | E78: Quantity decreases | F78: As expected | G78: Pass
A79: PROD-18 | B79: Product Details | C79: R05 | D79: Enter quantity 0 | E79: Invalid quantity rejected | F79: As expected | G79: Pass
A80: PROD-19 | B80: Product Details | C80: R05 | D80: Enter negative quantity | E80: Invalid input rejected | F80: As expected | G80: Pass
A81: PROD-20 | B81: Product Details | C81: R05 | D81: Enter letters in quantity | E81: Invalid input rejected | F81: As expected | G81: Pass
A82: FIL-01 | B82: Filter & Sort | C82: R06 | D82: Filter by category | E82: Correct products displayed | F82: As expected | G82: Pass
A83: FIL-02 | B83: Filter & Sort | C83: R06 | D83: Filter by brand | E83: Correct products displayed | F83: As expected | G83: Pass
A84: FIL-03 | B84: Filter & Sort | C84: R06 | D84: Filter by minimum price | E84: Matching products displayed | F84: As expected | G84: Pass
A85: FIL-04 | B85: Filter & Sort | C85: R06 | D85: Filter by maximum price | E85: Matching products displayed | F85: As expected | G85: Pass
A86: FIL-05 | B86: Filter & Sort | C86: R06 | D86: Filter by price range | E86: Products within range displayed | F86: As expected | G86: Pass
A87: FIL-06 | B87: Filter & Sort | C87: R06 | D87: Filter by rating | E87: Matching ratings displayed | F87: As expected | G87: Pass
A88: FIL-07 | B88: Filter & Sort | C88: R06 | D88: Apply multiple filters | E88: Products satisfy selected filters | F88: As expected | G88: Pass
... A94: FIL-13 | B94: Filter & Sort | C94: R07 | D94: Apply filter with no results | E94: No-results message | F94: As expected | G94: Pass
A95: FIL-14 | B95: Filter & Sort | C95: R07 | D95: Invalid price range | E95: Validation displayed | F95: No validation for invalid price range | G95: Fail | H95: D06
A96: FIL-15 | B96: Filter & Sort | C96: R07 | D96: Refresh after filtering | E96: Behavior matches requirements | F96: As expected | G96: Pass
A97: CART-01 | B97: Cart | C97: R08 | D97: Add product to cart | E97: Product added | F97: As expected | G97: Pass
A98: CART-02 | B98: Cart | C98: R08 | D98: Add two different products | E98: Both products displayed | F98: As expected | G98: Pass
A99: CART-03 | B99: Cart | C99: R08 | D99: Add same product twice | E99: Quantity/line item handled correctly | F99: As expected | G99: Pass
A100: CART-04 | B100: Cart | C100: R08 | D100: View cart | E100: Cart page opens | F100: As expected | G100: Pass
A101: CART-05 | B101: Cart | C101: R08 | D101: Remove product | E101: Product removed | F101: As expected | G101: Pass
A102: CART-06 | B102: Cart | C102: R08 | D102: Increase quantity | E102: Quantity increases | F102: As expected | G102: Pass
A103: CART-07 | B103: Cart | C103: R08 | D103: Decrease quantity | E103: Quantity decreases | F103: As expected | G103: Pass
A104: CART-08 | B104: Cart | C104: R08 | D104: Set quantity to 0 | E104: Item removed or validation shown | F104: As expected | G104: Pass
A105: CART-09 | B105: Cart | C105: R08 | D105: Verify product price | E105: Correct price displayed | F105: As expected | G105: Pass
A106: CART-10 | B106: Cart | C106: R08 | D106: Verify subtotal | E106: Correct subtotal | F106: As expected | G106: Pass
A107: CART-11 | B107: Cart | C107: R08 | D107: Verify total | E107: Correct total | F107: As expected | G107: Pass
A108: CART-12 | B108: Cart | C108: R08 | D108: Apply valid coupon | E108: Discount applied | F108: As expected | G108: Pass
A109: CART-13 | B109: Cart | C109: R08 | D109: Apply invalid coupon | E109: Error displayed | F109: No error for invalid coupon | G109: Fail | H109: D05
A110: CART-14 | B110: Cart | C110: R08 | D110: Remove coupon | E110: Discount removed | F110: As expected | G110: Pass
A111: CART-15 | B111: Cart | C111: R08 | D111: Add out-of-stock product | E111: Product not added | F111: Out-of-stock product added to cart | G111: Fail | H111: D03
A112: CART-16 | B112: Cart | C112: R08 | D112: Refresh cart | E112: Cart state handled correctly | F112: As expected | G112: Pass
A113: CART-17 | B113: Cart | C113: R08 | D113: Empty cart | E113: Empty-cart message displayed | F113: As expected | G113: Pass
A114: CART-18 | B114: Cart | C114: R08 | D114: Continue shopping | E114: User returns to products | F114: As expected | G114: Pass
A115: CART-19 | B115: Cart | C115: R08 | D115: Proceed to checkout | E115: Checkout opens | F115: As expected | G115: Pass
A116: CART-20 | B116: Cart | C116: R08 | D116: Verify cart on mobile | E116: Cart usable | F116: As expected | G116: Pass
A117: WISH-01 | B117: Wishlist | C117: R09 | D117: Add product to wishlist | E117: Product added | F117: As expected | G117: Pass
A118: WISH-02 | B118: Wishlist | C118: R09 | D118: Remove product | E118: Product removed | F118: As expected | G118: Pass
A119: WISH-03 | B119: Wishlist | C119: R09 | D119: Add same product twice | E119: Duplicate handled | F119: As expected | G119: Pass
A120: WISH-04 | B120: Wishlist | C120: R09 | D120: Open wishlist | E120: Wishlist displayed | F120: As expected | G120: Pass
A121: WISH-05 | B121: Wishlist | C121: R09 | D121: Move wishlist item to cart | E121: Product added to cart | F121: As expected | G121: Pass
A122: WISH-06 | B122: Wishlist | C122: R09 | D122: Add unavailable product | E122: Behavior handled correctly | F122: As expected | G122: Pass
A123: WISH-07 | B123: Wishlist | C123: R09 | D123: Wishlist for logged-out user | E123: Login/request handled | F123: As expected | G123: Pass
... A134: CHK-10 | B134: Checkout | C134: R10 | D134: Verify order summary | E134: Correct products displayed | F134: As expected | G134: Pass
A135: CHK-11 | B135: Checkout | C135: R10 | D135: Verify total amount | E135: Total calculated correctly | F135: Total amount incorrect when coupon applied | G135: Fail | H135: D04
A136: CHK-12 | B136: Checkout | C136: R10 | D136: Select payment method | E136: Payment option selected | F136: As expected | G136: Pass
A137: CHK-13 | B137: Checkout | C137: R10 | D137: Change payment method | E137: New method selected | F137: As expected | G137: Pass
A138: CHK-14 | B138: Checkout | C138: R10 | D138: Place order | E138: Order created | F138: As expected | G138: Pass
A139: CHK-15 | B139: Checkout | C139: R10 | D139: Empty cart checkout | E139: Checkout blocked | F139: As expected | G139: Pass
A140: PAY-01 | B140: Payment | C140: R11 | D140: Pay using valid card | E140: Payment succeeds | F140: As expected | G140: Pass
A141: PAY-02 | B141: Payment | C141: R11 | D141: Invalid card number | E141: Error displayed | F141: As expected | G141: Pass
A142: PAY-03 | B142: Payment | C142: R11 | D142: Expired card | E142: Payment rejected | F142: As expected | G142: Pass
A143: PAY-04 | B143: Payment | C143: R11 | D143: Invalid CVV | E143: Error displayed | F143: As expected | G143: Pass
A144: PAY-05 | B144: Payment | C144: R11 | D144: Empty card details | E144: Validation displayed | F144: As expected | G144: Pass
A145: PAY-06 | B145: Payment | C145: R11 | D145: Pay using UPI | E145: Payment succeeds | F145: As expected | G145: Pass
A146: PAY-07 | B146: Payment | C146: R11 | D146: Invalid UPI ID | E146: Error displayed | F146: As expected | G146: Pass
A147: PAY-08 | B147: Payment | C147: R11 | D147: Cancel payment | E147: Payment cancelled | F147: As expected | G147: Pass
A148: PAY-09 | B148: Payment | C148: R11 | D148: Payment timeout | E148: Appropriate failure message | F148: As expected | G148: Pass
A149: PAY-10 | B149: Payment | C149: R11 | D149: Payment failure | E149: Order status handled correctly | F149: Order status incorrect after payment failure | G149: Fail | H149: D01
A150: PAY-11 | B150: Payment | C150: R11 | D150: Successful payment | E150: Confirmation displayed | F150: As expected | G150: Pass
A151: PAY-12 | B151: Payment | C151: R11 | D151: Refresh during payment | E151: Transaction handled safely | F151: As expected | G151: Pass
A152: PAY-13 | B152: Payment | C152: R11 | D152: Double-click Pay button | E152: Duplicate payment/order prevented | F152: Duplicate payment/order created on double-click | G152: Fail | H152: D02
A153: PAY-14 | B153: Payment | C153: R11 | D153: Payment receipt | E153: Receipt generated | F153: As expected | G153: Pass
...

Sheet Requirements
A1: Req ID | B1: Module | C1: Requirement | D1: Covered by Test Cases | E1: Test Cases Mapped | F1: Executed (Pass+Fail) | G1: Tested?
A2: R01 | B2: Registration | C2: User should be able to create an account with valid details | D2: REG-01 to REG-18 | E2: =COUNTIF('Test Cases'!$C$2:$C$174,A2) -> 18 | F2: =COUNTIFS('Test Cases'!$C$2:$C$174,A2,'Test Cases'!$G$2:$G$174,"Pass")+COUNTIFS('Test Cases'!$C$2:$C$174,A2,'Test Cases'!$G$2:$G$174,"Fail") -> 18 | G2: =IF(F2>0,"Yes","No") -> Yes
A3: R02 | B3: Login | C3: User should be able to log in with valid credentials | D3: LOG-01 to LOG-15 | E3: =COUNTIF('Test Cases'!$C$2:$C$174,A3) -> 15 | F3: =COUNTIFS('Test Cases'!$C$2:$C$174,A3,'Test Cases'!$G$2:$G$174,"Pass")+COUNTIFS('Test Cases'!$C$2:$C$174,A3,'Test Cases'!$G$2:$G$174,"Fail") -> 15 | G3: =IF(F3>0,"Yes","No") -> Yes
A4: R03 | B4: Home | C4: Website should display the home page correctly | D4: HOME-01 to HOME-12 | E4: =COUNTIF('Test Cases'!$C$2:$C$174,A4) -> 12 | F4: =COUNTIFS('Test Cases'!$C$2:$C$174,A4,'Test Cases'!$G$2:$G$174,"Pass")+COUNTIFS('Test Cases'!$C$2:$C$174,A4,'Test Cases'!$G$2:$G$174,"Fail") -> 12 | G4: =IF(F4>0,"Yes","No") -> Yes
A5: R04 | B5: Search | C5: User should be able to search for products | D5: SRCH-01 to SRCH-15 | E5: =COUNTIF('Test Cases'!$C$2:$C$174,A5) -> 15 | F5: =COUNTIFS('Test Cases'!$C$2:$C$174,A5,'Test Cases'!$G$2:$G$174,"Pass")+COUNTIFS('Test Cases'!$C$2:$C$174,A5,'Test Cases'!$G$2:$G$174,"Fail") -> 15 | G5: =IF(F5>0,"Yes","No") -> Yes
A6: R05 | B6: Product | C6: Product details, price, image and availability should be displayed | D6: PROD-01 to PROD-20 | E6: =COUNTIF('Test Cases'!$C$2:$C$174,A6) -> 20 | F6: =COUNTIFS('Test Cases'!$C$2:$C$174,A6,'Test Cases'!$G$2:$G$174,"Pass")+COUNTIFS('Test Cases'!$C$2:$C$174,A6,'Test Cases'!$G$2:$G$174,"Fail") -> 20 | G6: =IF(F6>0,"Yes","No") -> Yes
A7: R06 | B7: Filter | C7: User should be able to filter products | D7: FIL-01 to FIL-08 | E7: =COUNTIF('Test Cases'!$C$2:$C$174,A7) -> 8 | F7: =COUNTIFS('Test Cases'!$C$2:$C$174,A7,'Test Cases'!$G$2:$G$174,"Pass")+COUNTIFS('Test Cases'!$C$2:$C$174,A7,'Test Cases'!$G$2:$G$174,"Fail") -> 8 | G7: =IF(F7>0,"Yes","No") -> Yes
A8: R07 | B8: Sort | C8: User should be able to sort products by price/rating | D8: FIL-09 to FIL-15 | E8: =COUNTIF('Test Cases'!$C$2:$C$174,A8) -> 7 | F8: =COUNTIFS('Test Cases'!$C$2:$C$174,A8,'Test Cases'!$G$2:$G$174,"Pass")+COUNTIFS('Test Cases'!$C$2:$C$174,A8,'Test Cases'!$G$2:$G$174,"Fail") -> 7 | G8: =IF(F8>0,"Yes","No") -> Yes
A9: R08 | B9: Cart | C9: User should be able to add, remove and update products | D9: CART-01 to CART-20 | E9: =COUNTIF('Test Cases'!$C$2:$C$174,A9) -> 20 | F9: =COUNTIFS('Test Cases'!$C$2:$C$174,A9,'Test Cases'!$G$2:$G$174,"Pass")+COUNTIFS('Test Cases'!$C$2:$C$174,A9,'Test Cases'!$G$2:$G$174,"Fail") -> 20 | G9: =IF(F9>0,"Yes","No") -> Yes
A10: R09 | B10: Wishlist | C10: User should be able to add/remove products from wishlist | D10: WISH-01 to WISH-08 | E10: =COUNTIF('Test Cases'!$C$2:$C$174,A10) -> 8 | F10: =COUNTIFS('Test Cases'!$C$2:$C$174,A10,'Test Cases'!$G$2:$G$174,"Pass")+COUNTIFS('Test Cases'!$C$2:$C$174,A10,'Test Cases'!$G$2:$G$174,"Fail") -> 8 | G10: =IF(F10>0,"Yes","No") -> Yes
A11: R10 | B11: Checkout | C11: User should be able to enter and manage delivery address | D11: CHK-01 to CHK-15 | E11: =COUNTIF('Test Cases'!$C$2:$C$174,A11) -> 15 | F11: =COUNTIFS('Test Cases'!$C$2:$C$174,A11,'Test Cases'!$G$2:$G$174,"Pass")+COUNTIFS('Test Cases'!$C$2:$C$174,A11,'Test Cases'!$G$2:$G$174,"Fail") -> 15 | G11: =IF(F11>0,"Yes","No") -> Yes
A12: R11 | B12: Payment | C12: User should be able to make payment using available methods | D12: PAY-01 to PAY-15 | E12: =COUNTIF('Test Cases'!$C$2:$C$174,A12) -> 15 | F12: =COUNTIFS('Test Cases'!$C$2:$C$174,A12,'Test Cases'!$G$2:$G$174,"Pass")+COUNTIFS('Test Cases'!$C$2:$C$174,A12,'Test Cases'!$G$2:$G$174,"Fail") -> 15 | G12: =IF(F12>0,"Yes","No") -> Yes
A13: R12 | B13: Order | C13: User should be able to view and track orders | D13: ORD-01 to ORD-10 | E13: =COUNTIF('Test Cases'!$C$2:$C$174,A13) -> 10 | F13: =COUNTIFS('Test Cases'!$C$2:$C$174,A13,'Test Cases'!$G$2:$G$174,"Pass")+COUNTIFS('Test Cases'!$C$2:$C$174,A13,'Test Cases'!$G$2:$G$174,"Fail") -> 10 | G13: =IF(F13>0,"Yes","No") -> Yes
... A15: R14 | B15: Logout | C15: User should be able to securely log out | D15: PROF-10 | E15: =COUNTIF('Test Cases'!$C$2:$C$174,A15) -> 1 | F15: =COUNTIFS('Test Cases'!$C$2:$C$174,A15,'Test Cases'!$G$2:$G$174,"Pass")+COUNTIFS('Test Cases'!$C$2:$C$174,A15,'Test Cases'!$G$2:$G$174,"Fail") -> 1 | G15: =IF(F15>0,"Yes","No") -> Yes
A17: "Tested?" is calculated: a requirement counts as tested when at least one of its mapped test cases has been executed (Pass or Fail).

Sheet Defects
A1: Defect ID | B1: Module | C1: Failed TCs (count) | D1: Summary | E1: Severity | F1: Status
A2: D01 | B2: Payment | C2: =COUNTIF('Test Cases'!$H$2:$H$174,A2) -> 2 | D2: Order status incorrect after payment failure / retry fails | E2: Critical | F2: Open
A3: D02 | B3: Payment | C3: =COUNTIF('Test Cases'!$H$2:$H$174,A3) -> 1 | D3: Duplicate payment/order created on double-click of Pay | E3: Critical | F3: Open
A4: D03 | B4: Product Details / Cart | C4: =COUNTIF('Test Cases'!$H$2:$H$174,A4) -> 2 | D4: Out-of-stock product can be purchased / added to cart | E4: High | F4: Open
A5: D04 | B5: Checkout | C5: =COUNTIF('Test Cases'!$H$2:$H$174,A5) -> 1 | D5: Total amount incorrect when coupon applied | E5: High | F5: Open
A6: D05 | B6: Cart | C6: =COUNTIF('Test Cases'!$H$2:$H$174,A6) -> 1 | D6: No error message for invalid coupon | E6: Medium | F6: Open
A7: D06 | B7: Filter & Sort | C7: =COUNTIF('Test Cases'!$H$2:$H$174,A7) -> 1 | D7: No validation for invalid price range | E7: Medium | F7: Open
A8: D07 | B8: Product Search | C8: =COUNTIF('Test Cases'!$H$2:$H$174,A8) -> 1 | D8: Empty search shows all products without message | E8: Medium | F8: Open
A9: D08 | B9: Home Page | C9: =COUNTIF('Test Cases'!$H$2:$H$174,A9) -> 1 | D9: Broken image on home page | E9: Low | F9: Open
A10: Total | C10: =SUM(C2:C9) -> 10
A12: The 10 failed test cases map to 8 unique defects (several failures share one root cause). The problem statement gives only the counts (2 Critical, 2 High, 3 Medium, 1 Low); descriptions and modules are illustrative. Link test cases to defects using the Defect ID column on Test Cases.

Sheet Response Times
A1: Test # | B1: Page Loading Time (sec)
A2: Test 1 | B2: 2
A3: Test 2 | B3: 3
A4: Test 3 | B4: 4
A5: Test 4 | B5: 3
A6: Test 5 | B6: 8
A8: Page-loading times from five performance test executions (blue = editable).
